voltkit/__init__.py
voltkit/core/__init__.py
voltkit/core/bode.py
voltkit/core/dc_ac.py
voltkit/core/fft.py
voltkit/core/filters.py
voltkit/core/impedance.py
voltkit/core/ohms_law.py
voltkit/core/phasor_diagram.py
voltkit/core/phasors.py
voltkit/core/power.py
voltkit/core/resistors.py
voltkit/core/signal_loading.py
voltkit/core/signal_stats.py
voltkit/core/signal_transformation.py
voltkit/core/signals.py
voltkit/core/simulator.py
voltkit/core/transient.py
voltkit/core/units.py
voltkit-1.1.0.dist-info/licenses/LICENSE
voltkit-1.1.0.dist-info/METADATA
voltkit-1.1.0.dist-info/WHEEL
voltkit-1.1.0.dist-info/top_level.txt
voltkit-1.1.0.dist-info/RECORD
