Metadata-Version: 2.4
Name: voltkit
Version: 1.1.0
Summary: VoltKit: A Python toolkit for electrical and electronics engineering
Home-page: https://github.com/ShobhitBhardwaj763/voltkit
Author: Shobhit Bhardwaj
Author-email: voltkit.dev@gmail.com
Keywords: electrical engineering simulation education phasors fft bode streamlit
Classifier: Programming Language :: Python :: 3
Classifier: License :: OSI Approved :: MIT License
Classifier: Operating System :: OS Independent
Classifier: Intended Audience :: Education
Classifier: Topic :: Scientific/Engineering :: Electronic Design Automation (EDA)
Requires-Python: >=3.7
License-File: LICENSE
Requires-Dist: numpy
Requires-Dist: matplotlib
Requires-Dist: scipy
Requires-Dist: streamlit
Requires-Dist: pandas
Dynamic: author
Dynamic: author-email
Dynamic: classifier
Dynamic: description
Dynamic: description-content-type
Dynamic: home-page
Dynamic: keywords
Dynamic: license-file
Dynamic: requires-dist
Dynamic: requires-python
Dynamic: summary
